benchmake/BenchMake.py
benchmake/__init__.py
benchmake-1.1.2.dist-info/licenses/LICENSE
benchmake-1.1.2.dist-info/METADATA
benchmake-1.1.2.dist-info/WHEEL
benchmake-1.1.2.dist-info/top_level.txt
benchmake-1.1.2.dist-info/RECORD
