Metadata-Version: 2.4
Name: benchmake
Version: 1.1.2
Summary: A lightweight benchmarking toolkit for Python, helping you measure and compare code performance with ease.
Author: Prof Dr Amanda S Barnard
License-Expression: MIT
Keywords: benchmark,performance,tooling
Classifier: Development Status :: 5 - Production/Stable
Classifier: Intended Audience :: Science/Research
Classifier: Programming Language :: Python :: 3.8
Classifier: Operating System :: OS Independent
Requires-Python: >=3.6
License-File: LICENSE
Requires-Dist: numpy
Requires-Dist: pandas
Requires-Dist: joblib
Requires-Dist: scikit-learn
Dynamic: license-file
